crispr_millipede_helper/__init__.py
crispr_millipede_helper/models/__init__.py
crispr_millipede_helper/models/pipeline_models.py
crispr_millipede_helper/pipeline/__init__.py
crispr_millipede_helper/pipeline/PipelineProcessing.py
crispr_millipede_helper-0.1.18.dist-info/METADATA
crispr_millipede_helper-0.1.18.dist-info/WHEEL
crispr_millipede_helper-0.1.18.dist-info/RECORD
