Metadata-Version: 2.1
Name: crispr-millipede-helper
Version: 0.1.18
Summary: 
Author: Basheer Becerra
Author-email: bbecerr@outlook.com
Requires-Python: >=3.8,<3.12
Classifier: Programming Language :: Python :: 3
Classifier: Programming Language :: Python :: 3.8
Classifier: Programming Language :: Python :: 3.9
Classifier: Programming Language :: Python :: 3.10
Classifier: Programming Language :: Python :: 3.11
Requires-Dist: PyMuPDF (==1.24.7)
Requires-Dist: biopython (>=1.81,<2.0)
Requires-Dist: google-cloud-storage (==3.1.0)
Requires-Dist: matplotlib (>=3.7.1,<4.0.0)
Requires-Dist: numpy (==1.24.4)
Requires-Dist: pandarallel (>=1.6.4,<2.0.0)
Requires-Dist: pandas (>=1.5.3,<2.0.0)
Requires-Dist: scipy (>=1.10.1,<2.0.0)
Requires-Dist: typeguard (>=3.0.2,<4.0.0)
